[{"timestamp":1605451949972,"files":[{"filename":"index.html","previous":449,"size":450,"diff":1},{"filename":"static/js/0.********.chunk.js","previous":33280,"size":31455,"diff":-1825},{"filename":"static/js/4.********.chunk.js","previous":9355,"size":9537,"diff":182},{"filename":"static/js/5.********.chunk.js","previous":2605,"size":2898,"diff":293},{"filename":"static/js/6.********.chunk.js","previous":159020,"size":159020,"diff":0},{"filename":"static/js/7.********.chunk.js","previous":35966,"size":35971,"diff":5},{"filename":"static/js/8.********.chunk.js","previous":127,"size":127,"diff":0},{"filename":"static/js/main.********.chunk.js","previous":1655,"size":1674,"diff":19},{"filename":"static/js/runtime.********.js","previous":1574,"size":1601,"diff":27},{"filename":"sw.js","previous":4157,"size":4157,"diff":0},{"filename":"static/js/3.********.chunk.js","previous":86397,"size":86396,"diff":-1},{"filename":"static/css/5.78cdbd99.chunk.css","previous":972,"size":0,"diff":-972},{"filename":"static/css/main.6daadbc9.chunk.css","previous":917,"size":0,"diff":-917},{"filename":"static/css/4.cb7e0a4d.chunk.css","previous":2988,"size":0,"diff":-2988},{"filename":"static/css/main.ff4e4095.chunk.css","previous":0,"size":914,"diff":914},{"filename":"static/css/4.6e854426.chunk.css","previous":0,"size":3043,"diff":3043},{"filename":"static/css/5.6ba5d694.chunk.css","previous":0,"size":998,"diff":998}]},{"timestamp":1603375168479,"files":[{"filename":"index.html","previous":450,"size":449,"diff":-1},{"filename":"static/js/0.********.chunk.js","previous":33280,"size":33280,"diff":0},{"filename":"static/js/4.********.chunk.js","previous":9355,"size":9355,"diff":0},{"filename":"static/js/5.********.chunk.js","previous":2604,"size":2605,"diff":1},{"filename":"static/js/6.********.chunk.js","previous":159020,"size":159020,"diff":0},{"filename":"static/js/7.********.chunk.js","previous":35966,"size":35966,"diff":0},{"filename":"static/js/8.********.chunk.js","previous":127,"size":127,"diff":0},{"filename":"static/js/main.********.chunk.js","previous":1655,"size":1655,"diff":0},{"filename":"static/js/runtime.********.js","previous":1577,"size":1574,"diff":-3},{"filename":"sw.js","previous":4159,"size":4157,"diff":-2},{"filename":"static/js/3.********.chunk.js","previous":86397,"size":86397,"diff":0},{"filename":"static/css/5.78cdbd99.chunk.css","previous":972,"size":972,"diff":0},{"filename":"static/css/main.6daadbc9.chunk.css","previous":917,"size":917,"diff":0},{"filename":"static/css/4.cb7e0a4d.chunk.css","previous":2988,"size":2988,"diff":0}]},{"timestamp":1603303578470,"files":[{"filename":"index.html","previous":452,"size":450,"diff":-2},{"filename":"static/js/0.********.chunk.js","previous":33280,"size":33280,"diff":0},{"filename":"static/js/4.********.chunk.js","previous":9325,"size":9355,"diff":30},{"filename":"static/js/5.********.chunk.js","previous":2604,"size":2604,"diff":0},{"filename":"static/js/6.********.chunk.js","previous":159020,"size":159020,"diff":0},{"filename":"static/js/7.********.chunk.js","previous":35966,"size":35966,"diff":0},{"filename":"static/js/8.********.chunk.js","previous":127,"size":127,"diff":0},{"filename":"static/js/main.********.chunk.js","previous":1655,"size":1655,"diff":0},{"filename":"static/js/runtime.********.js","previous":1578,"size":1577,"diff":-1},{"filename":"sw.js","previous":4162,"size":4159,"diff":-3},{"filename":"static/js/3.********.chunk.js","previous":86397,"size":86397,"diff":0},{"filename":"static/css/5.78cdbd99.chunk.css","previous":972,"size":972,"diff":0},{"filename":"static/css/main.920392d8.chunk.css","previous":917,"size":0,"diff":-917},{"filename":"static/css/4.4fac4bb2.chunk.css","previous":2989,"size":0,"diff":-2989},{"filename":"static/css/main.6daadbc9.chunk.css","previous":0,"size":917,"diff":917},{"filename":"static/css/4.cb7e0a4d.chunk.css","previous":0,"size":2988,"diff":2988}]},{"timestamp":1603054367777,"files":[{"filename":"index.html","previous":451,"size":452,"diff":1},{"filename":"static/js/0.********.chunk.js","previous":33277,"size":33280,"diff":3},{"filename":"static/js/4.********.chunk.js","previous":9327,"size":9325,"diff":-2},{"filename":"static/js/5.********.chunk.js","previous":2604,"size":2604,"diff":0},{"filename":"static/js/6.********.chunk.js","previous":159020,"size":159020,"diff":0},{"filename":"static/js/7.********.chunk.js","previous":32941,"size":35966,"diff":3025},{"filename":"static/js/8.********.chunk.js","previous":127,"size":127,"diff":0},{"filename":"static/js/main.********.chunk.js","previous":1655,"size":1655,"diff":0},{"filename":"static/js/runtime.********.js","previous":1572,"size":1578,"diff":6},{"filename":"sw.js","previous":4163,"size":4162,"diff":-1},{"filename":"static/js/3.********.chunk.js","previous":86243,"size":86397,"diff":154},{"filename":"static/css/main.9bfdc382.chunk.css","previous":916,"size":0,"diff":-916},{"filename":"static/css/4.cdc57a1a.chunk.css","previous":2990,"size":0,"diff":-2990},{"filename":"static/css/5.78cdbd99.chunk.css","previous":972,"size":972,"diff":0},{"filename":"static/css/main.920392d8.chunk.css","previous":0,"size":917,"diff":917},{"filename":"static/css/4.4fac4bb2.chunk.css","previous":0,"size":2989,"diff":2989}]},{"timestamp":1603053189884,"files":[{"filename":"index.html","previous":450,"size":451,"diff":1},{"filename":"static/css/main.187de001.chunk.css","previous":1501,"size":0,"diff":-1501},{"filename":"static/js/0.********.chunk.js","previous":33277,"size":33277,"diff":0},{"filename":"static/js/4.********.chunk.js","previous":9406,"size":9327,"diff":-79},{"filename":"static/js/5.********.chunk.js","previous":2605,"size":2604,"diff":-1},{"filename":"static/js/6.********.chunk.js","previous":159020,"size":159020,"diff":0},{"filename":"static/js/7.********.chunk.js","previous":32941,"size":32941,"diff":0},{"filename":"static/js/8.********.chunk.js","previous":127,"size":127,"diff":0},{"filename":"static/js/main.********.chunk.js","previous":1694,"size":1655,"diff":-39},{"filename":"static/js/runtime.********.js","previous":1576,"size":1572,"diff":-4},{"filename":"sw.js","previous":4163,"size":4163,"diff":0},{"filename":"static/css/5.da9f9abb.chunk.css","previous":968,"size":0,"diff":-968},{"filename":"static/js/3.********.chunk.js","previous":86240,"size":86243,"diff":3},{"filename":"static/css/4.f85a8fec.chunk.css","previous":3052,"size":0,"diff":-3052},{"filename":"static/css/main.9bfdc382.chunk.css","previous":0,"size":916,"diff":916},{"filename":"static/css/4.cdc57a1a.chunk.css","previous":0,"size":2990,"diff":2990},{"filename":"static/css/5.78cdbd99.chunk.css","previous":0,"size":972,"diff":972}]},{"timestamp":1602617878993,"files":[{"filename":"index.html","previous":452,"size":450,"diff":-2},{"filename":"static/css/main.187de001.chunk.css","previous":1501,"size":1501,"diff":0},{"filename":"static/js/0.********.chunk.js","previous":29633,"size":33277,"diff":3644},{"filename":"static/js/4.********.chunk.js","previous":86243,"size":9406,"diff":-76837},{"filename":"static/js/5.********.chunk.js","previous":2605,"size":2605,"diff":0},{"filename":"static/js/6.********.chunk.js","previous":3007,"size":159020,"diff":156013},{"filename":"static/js/7.********.chunk.js","previous":4280,"size":32941,"diff":28661},{"filename":"static/js/8.********.chunk.js","previous":3397,"size":127,"diff":-3270},{"filename":"static/js/main.********.chunk.js","previous":1697,"size":1694,"diff":-3},{"filename":"static/js/runtime.********.js","previous":1654,"size":1576,"diff":-78},{"filename":"sw.js","previous":4392,"size":4163,"diff":-229},{"filename":"static/css/5.da9f9abb.chunk.css","previous":968,"size":968,"diff":0},{"filename":"static/js/1.********.chunk.js","previous":3932,"size":0,"diff":-3932},{"filename":"static/css/6.3d153530.chunk.css","previous":1217,"size":0,"diff":-1217},{"filename":"static/css/7.1624eb88.chunk.css","previous":1404,"size":0,"diff":-1404},{"filename":"static/css/8.9005d853.chunk.css","previous":1322,"size":0,"diff":-1322},{"filename":"static/js/9.********.chunk.js","previous":159021,"size":0,"diff":-159021},{"filename":"static/css/10.753685f8.chunk.css","previous":919,"size":0,"diff":-919},{"filename":"static/js/10.********.chunk.js","previous":3240,"size":0,"diff":-3240},{"filename":"static/js/11.********.chunk.js","previous":32944,"size":0,"diff":-32944},{"filename":"static/js/12.********.chunk.js","previous":129,"size":0,"diff":-129},{"filename":"static/js/3.********.chunk.js","previous":0,"size":86240,"diff":86240},{"filename":"static/css/4.f85a8fec.chunk.css","previous":0,"size":3052,"diff":3052}]},{"timestamp":1602616736742,"files":[{"filename":"index.html","previous":450,"size":452,"diff":2},{"filename":"static/css/4.f85a8fec.chunk.css","previous":3052,"size":0,"diff":-3052},{"filename":"static/css/main.187de001.chunk.css","previous":1501,"size":1501,"diff":0},{"filename":"static/js/0.********.chunk.js","previous":33277,"size":29633,"diff":-3644},{"filename":"static/js/3.********.chunk.js","previous":86240,"size":0,"diff":-86240},{"filename":"static/js/4.********.chunk.js","previous":9406,"size":86243,"diff":76837},{"filename":"static/js/5.********.chunk.js","previous":2605,"size":2605,"diff":0},{"filename":"static/js/6.********.chunk.js","previous":159020,"size":3007,"diff":-156013},{"filename":"static/js/7.********.chunk.js","previous":32941,"size":4280,"diff":-28661},{"filename":"static/js/8.********.chunk.js","previous":127,"size":3397,"diff":3270},{"filename":"static/js/main.********.chunk.js","previous":1694,"size":1697,"diff":3},{"filename":"static/js/runtime.********.js","previous":1576,"size":1654,"diff":78},{"filename":"sw.js","previous":4163,"size":4392,"diff":229},{"filename":"static/css/5.da9f9abb.chunk.css","previous":968,"size":968,"diff":0},{"filename":"static/js/1.********.chunk.js","previous":0,"size":3932,"diff":3932},{"filename":"static/css/6.3d153530.chunk.css","previous":0,"size":1217,"diff":1217},{"filename":"static/css/7.1624eb88.chunk.css","previous":0,"size":1404,"diff":1404},{"filename":"static/css/8.9005d853.chunk.css","previous":0,"size":1322,"diff":1322},{"filename":"static/js/9.********.chunk.js","previous":0,"size":159021,"diff":159021},{"filename":"static/css/10.753685f8.chunk.css","previous":0,"size":919,"diff":919},{"filename":"static/js/10.********.chunk.js","previous":0,"size":3240,"diff":3240},{"filename":"static/js/11.********.chunk.js","previous":0,"size":32944,"diff":32944},{"filename":"static/js/12.********.chunk.js","previous":0,"size":129,"diff":129}]},{"timestamp":1602616527269,"files":[{"filename":"index.html","previous":450,"size":450,"diff":0},{"filename":"static/css/4.f85a8fec.chunk.css","previous":3052,"size":3052,"diff":0},{"filename":"static/css/main.187de001.chunk.css","previous":1501,"size":1501,"diff":0},{"filename":"static/js/0.********.chunk.js","previous":33277,"size":33277,"diff":0},{"filename":"static/js/3.********.chunk.js","previous":86240,"size":86240,"diff":0},{"filename":"static/js/4.********.chunk.js","previous":9442,"size":9406,"diff":-36},{"filename":"static/js/5.********.chunk.js","previous":2607,"size":2605,"diff":-2},{"filename":"static/js/6.********.chunk.js","previous":159020,"size":159020,"diff":0},{"filename":"static/js/7.********.chunk.js","previous":32941,"size":32941,"diff":0},{"filename":"static/js/8.********.chunk.js","previous":127,"size":127,"diff":0},{"filename":"static/js/main.********.chunk.js","previous":1710,"size":1694,"diff":-16},{"filename":"static/js/runtime.********.js","previous":1571,"size":1576,"diff":5},{"filename":"sw.js","previous":4157,"size":4163,"diff":6},{"filename":"static/css/5.da9f9abb.chunk.css","previous":968,"size":968,"diff":0}]},{"timestamp":1602594558263,"files":[{"filename":"index.html","previous":451,"size":450,"diff":-1},{"filename":"static/css/4.f85a8fec.chunk.css","previous":3052,"size":3052,"diff":0},{"filename":"static/css/main.187de001.chunk.css","previous":1501,"size":1501,"diff":0},{"filename":"static/js/0.********.chunk.js","previous":33277,"size":33277,"diff":0},{"filename":"static/js/3.********.chunk.js","previous":86240,"size":86240,"diff":0},{"filename":"static/js/4.********.chunk.js","previous":9420,"size":9442,"diff":22},{"filename":"static/js/5.********.chunk.js","previous":2608,"size":2607,"diff":-1},{"filename":"static/js/6.********.chunk.js","previous":159020,"size":159020,"diff":0},{"filename":"static/js/7.********.chunk.js","previous":32941,"size":32941,"diff":0},{"filename":"static/js/8.********.chunk.js","previous":127,"size":127,"diff":0},{"filename":"static/js/main.********.chunk.js","previous":1706,"size":1710,"diff":4},{"filename":"static/js/runtime.********.js","previous":1575,"size":1571,"diff":-4},{"filename":"sw.js","previous":4163,"size":4157,"diff":-6},{"filename":"static/css/5.da9f9abb.chunk.css","previous":968,"size":968,"diff":0}]},{"timestamp":1602593638328,"files":[{"filename":"index.html","previous":450,"size":451,"diff":1},{"filename":"static/css/4.f85a8fec.chunk.css","previous":3052,"size":3052,"diff":0},{"filename":"static/css/5.47db7f1f.chunk.css","previous":955,"size":0,"diff":-955},{"filename":"static/css/main.187de001.chunk.css","previous":1501,"size":1501,"diff":0},{"filename":"static/js/0.********.chunk.js","previous":33277,"size":33277,"diff":0},{"filename":"static/js/3.********.chunk.js","previous":86240,"size":86240,"diff":0},{"filename":"static/js/4.********.chunk.js","previous":9420,"size":9420,"diff":0},{"filename":"static/js/5.********.chunk.js","previous":2608,"size":2608,"diff":0},{"filename":"static/js/6.********.chunk.js","previous":159020,"size":159020,"diff":0},{"filename":"static/js/7.********.chunk.js","previous":32941,"size":32941,"diff":0},{"filename":"static/js/8.********.chunk.js","previous":127,"size":127,"diff":0},{"filename":"static/js/main.********.chunk.js","previous":1706,"size":1706,"diff":0},{"filename":"static/js/runtime.********.js","previous":1572,"size":1575,"diff":3},{"filename":"sw.js","previous":4164,"size":4163,"diff":-1},{"filename":"static/css/5.da9f9abb.chunk.css","previous":0,"size":968,"diff":968}]}]
